{
  "heroes": [
    {
      "id": 1,
      "name": "Первый герой",
      "description": "Первый герой в рейтинге!",
      "element": "fire"
    },
    {
      "id": "a96f7d28-5173-4d25-a7ee-5162aeab357d",
      "name": "testy ytset",
      "description": "asd",
      "element": "fire"
    }
  ],
  "filters": [
    {
      "value": "all",
      "title": "All"
    },
    {
      "value": "fire",
      "title": "Fire"
    },
    {
      "value": "water",
      "title": "Water"
    },
    {
      "value": "wind",
      "title": "Wind"
    },
    {
      "value": "earth",
      "title": "Earth"
    }
  ]
}